{
    "1": {
        "name": "silent",
        "album": "silent",
        "artist": "SEKAI NO OWARI",
        "release_date": "2020-10-21",
        "length": 308921,
        "popularity": 57,
        "key": 0,
        "mode": 1,
        "danceability": 0.43,
        "acousticness": 0.434,
        "energy": 0.62,
        "instrumentalness": 0,
        "liveness": 0.209,
        "loudness": -5.274,
        "speechiness": 0.0419,
        "tempo": 176.14,
        "time_signature": 4,
        "valence": 0.424
    },
    "2": {
        "name": "アザトカワイイ",
        "album": "ひなたざか (TYPE-A)",
        "artist": "Hinatazaka46",
        "release_date": "2018",
        "length": 238533,
        "popularity": 7,
        "key": 6,
        "mode": 1,
        "danceability": 0.481,
        "acousticness": 0.158,
        "energy": 0.838,
        "instrumentalness": 0,
        "liveness": 0.095,
        "loudness": -3.577,
        "speechiness": 0.0592,
        "tempo": 159.977,
        "time_signature": 4,
        "valence": 0.608
    },
    "3": {
        "name": "ドライフラワー",
        "album": "ドライフラワー",
        "artist": "Yuuri",
        "release_date": "2020-10-25",
        "length": 285586,
        "popularity": 70,
        "key": 7,
        "mode": 1,
        "danceability": 0.463,
        "acousticness": 0.426,
        "energy": 0.624,
        "instrumentalness": 0,
        "liveness": 0.221,
        "loudness": -5.118,
        "speechiness": 0.0274,
        "tempo": 147.929,
        "time_signature": 4,
        "valence": 0.521
    },
    "4": {
        "name": "Not the End",
        "album": "Not the End",
        "artist": "Rei Yasuda",
        "release_date": "2021-02-07",
        "length": 343320,
        "popularity": 51,
        "key": 7,
        "mode": 1,
        "danceability": 0.376,
        "acousticness": 0.000592,
        "energy": 0.75,
        "instrumentalness": 0.000105,
        "liveness": 0.309,
        "loudness": -4.129,
        "speechiness": 0.0421,
        "tempo": 165.694,
        "time_signature": 4,
        "valence": 0.248
    },
    "5": {
        "name": "キンモクセイ",
        "album": "イラつくときはいつだって",
        "artist": "オレンジスパイニクラブ",
        "release_date": "2020-01-22",
        "length": 231435,
        "popularity": 1,
        "key": 5,
        "mode": 1,
        "danceability": 0.554,
        "acousticness": 0.0991,
        "energy": 0.761,
        "instrumentalness": 0,
        "liveness": 0.145,
        "loudness": -3.937,
        "speechiness": 0.034,
        "tempo": 105.041,
        "time_signature": 4,
        "valence": 0.327
    },
    "6": {
        "name": "スマイル",
        "album": "スマイル",
        "artist": "森七菜",
        "release_date": "2020-07-19",
        "length": 176800,
        "popularity": 56,
        "key": 1,
        "mode": 0,
        "danceability": 0.784,
        "acousticness": 0.15,
        "energy": 0.743,
        "instrumentalness": 0,
        "liveness": 0.295,
        "loudness": -4.842,
        "speechiness": 0.0303,
        "tempo": 123.986,
        "time_signature": 4,
        "valence": 0.886
    },
    "7": {
        "name": "勿忘",
        "album": "Grower",
        "artist": "Awesome City Club",
        "release_date": "2021-02-10",
        "length": 251533,
        "popularity": 73,
        "key": 6,
        "mode": 0,
        "danceability": 0.448,
        "acousticness": 0.234,
        "energy": 0.447,
        "instrumentalness": 0,
        "liveness": 0.382,
        "loudness": -7.161,
        "speechiness": 0.045,
        "tempo": 78.861,
        "time_signature": 4,
        "valence": 0.299
    },
    "8": {
        "name": "Mela!",
        "album": "Mela!",
        "artist": "Ryokuoushoku Shakai",
        "release_date": "2020-04-13",
        "length": 242066,
        "popularity": 73,
        "key": 8,
        "mode": 1,
        "danceability": 0.619,
        "acousticness": 0.0439,
        "energy": 0.941,
        "instrumentalness": 1.73e-05,
        "liveness": 0.318,
        "loudness": -1.618,
        "speechiness": 0.0584,
        "tempo": 137.967,
        "time_signature": 4,
        "valence": 0.624
    },
    "9": {
        "name": "恋人ごっこ",
        "album": "hope",
        "artist": "Macaroni Empitsu",
        "release_date": "2020-04-01",
        "length": 200219,
        "popularity": 66,
        "key": 1,
        "mode": 1,
        "danceability": 0.438,
        "acousticness": 0.124,
        "energy": 0.646,
        "instrumentalness": 0,
        "liveness": 0.0603,
        "loudness": -5.301,
        "speechiness": 0.0361,
        "tempo": 102.033,
        "time_signature": 4,
        "valence": 0.745
    },
    "10": {
        "name": "空と青",
        "album": "空と青",
        "artist": "Leo Ieiri",
        "release_date": "2021-01-13",
        "length": 260946,
        "popularity": 51,
        "key": 0,
        "mode": 1,
        "danceability": 0.419,
        "acousticness": 0.0511,
        "energy": 0.819,
        "instrumentalness": 2.61e-06,
        "liveness": 0.0778,
        "loudness": -3.2,
        "speechiness": 0.0442,
        "tempo": 190.001,
        "time_signature": 4,
        "valence": 0.601
    },
    "11": {
        "name": "千両役者",
        "album": "千両役者",
        "artist": "King Gnu",
        "release_date": "2020-12-02",
        "length": 180026,
        "popularity": 58,
        "key": 11,
        "mode": 0,
        "danceability": 0.33,
        "acousticness": 0.0112,
        "energy": 0.948,
        "instrumentalness": 0,
        "liveness": 0.375,
        "loudness": -4.492,
        "speechiness": 0.335,
        "tempo": 100.15,
        "time_signature": 3,
        "valence": 0.564
    },
    "12": {
        "name": "なぜ 恋をして来なかったんだろう?",
        "album": "Nobody's fault (Special Edition)",
        "artist": "櫻坂46",
        "release_date": "2020-12-09",
        "length": 209146,
        "popularity": 47,
        "key": 4,
        "mode": 0,
        "danceability": 0.544,
        "acousticness": 0.0308,
        "energy": 0.937,
        "instrumentalness": 0,
        "liveness": 0.0609,
        "loudness": -2.346,
        "speechiness": 0.0456,
        "tempo": 151.96,
        "time_signature": 4,
        "valence": 0.857
    },
    "13": {
        "name": "Dynamite",
        "album": "BE",
        "artist": "BTS",
        "release_date": "2020-11-20",
        "length": 199053,
        "popularity": 44,
        "key": 6,
        "mode": 0,
        "danceability": 0.746,
        "acousticness": 0.0112,
        "energy": 0.765,
        "instrumentalness": 0,
        "liveness": 0.0936,
        "loudness": -4.41,
        "speechiness": 0.0993,
        "tempo": 114.044,
        "time_signature": 4,
        "valence": 0.737
    },
    "14": {
        "name": "うっせぇわ",
        "album": "うっせぇわ",
        "artist": "Ado",
        "release_date": "2020-10-23",
        "length": 204920,
        "popularity": 68,
        "key": 11,
        "mode": 0,
        "danceability": 0.525,
        "acousticness": 0.00485,
        "energy": 0.978,
        "instrumentalness": 0,
        "liveness": 0.06,
        "loudness": -1.072,
        "speechiness": 0.0815,
        "tempo": 178.069,
        "time_signature": 4,
        "valence": 0.577
    },
    "15": {
        "name": "創造",
        "album": "創造",
        "artist": "Gen Hoshino",
        "release_date": "2021-02-17",
        "length": 234166,
        "popularity": 55,
        "key": 10,
        "mode": 0,
        "danceability": 0.724,
        "acousticness": 0.00617,
        "energy": 0.808,
        "instrumentalness": 0.000199,
        "liveness": 0.315,
        "loudness": -4.877,
        "speechiness": 0.0756,
        "tempo": 95.007,
        "time_signature": 4,
        "valence": 0.836
    },
    "16": {
        "name": "春を告げる",
        "album": "春を告げる",
        "artist": "yama",
        "release_date": "2020-04-17",
        "length": 196497,
        "popularity": 66,
        "key": 11,
        "mode": 1,
        "danceability": 0.548,
        "acousticness": 0.0397,
        "energy": 0.871,
        "instrumentalness": 0,
        "liveness": 0.357,
        "loudness": -5.377,
        "speechiness": 0.123,
        "tempo": 120.009,
        "time_signature": 4,
        "valence": 0.487
    },
    "17": {
        "name": "Stand by me, Stand by you.",
        "album": "Life Goes On",
        "artist": "HIRAIDAI",
        "release_date": "2021-02-10",
        "length": 193012,
        "popularity": 70,
        "key": 3,
        "mode": 1,
        "danceability": 0.66,
        "acousticness": 0.0879,
        "energy": 0.576,
        "instrumentalness": 0,
        "liveness": 0.0599,
        "loudness": -5.627,
        "speechiness": 0.0363,
        "tempo": 80.978,
        "time_signature": 4,
        "valence": 0.561
    },
    "18": {
        "name": "やさしさで溢れるように",
        "album": "What's Love?",
        "artist": "JUJU",
        "release_date": "2009-03-04",
        "length": 290773,
        "popularity": 0,
        "key": 5,
        "mode": 0,
        "danceability": 0.328,
        "acousticness": 0.327,
        "energy": 0.723,
        "instrumentalness": 0,
        "liveness": 0.114,
        "loudness": -4.105,
        "speechiness": 0.0365,
        "tempo": 78.559,
        "time_signature": 4,
        "valence": 0.374
    },
    "19": {
        "name": "点描の唄",
        "album": "青と夏",
        "artist": "Mrs. GREEN APPLE",
        "release_date": "2018-07-31",
        "length": 307066,
        "popularity": 73,
        "key": 0,
        "mode": 1,
        "danceability": 0.502,
        "acousticness": 0.447,
        "energy": 0.632,
        "instrumentalness": 0,
        "liveness": 0.103,
        "loudness": -4.612,
        "speechiness": 0.0273,
        "tempo": 152.014,
        "time_signature": 4,
        "valence": 0.308
    },
    "20": {
        "name": "春泥棒",
        "album": "春泥棒",
        "artist": "ヨルシカ",
        "release_date": "2021-01-09",
        "length": 290289,
        "popularity": 64,
        "key": 5,
        "mode": 1,
        "danceability": 0.762,
        "acousticness": 0.103,
        "energy": 0.595,
        "instrumentalness": 4.71e-05,
        "liveness": 0.115,
        "loudness": -6.777,
        "speechiness": 0.0445,
        "tempo": 125.047,
        "time_signature": 4,
        "valence": 0.858
    },
    "21": {
        "name": "栄光の架橋",
        "album": "ゆずイロハ1997-2017",
        "artist": "YUZU",
        "release_date": "2017-04-26",
        "length": 323000,
        "popularity": 54,
        "key": 4,
        "mode": 1,
        "danceability": 0.557,
        "acousticness": 0.789,
        "energy": 0.383,
        "instrumentalness": 0,
        "liveness": 0.107,
        "loudness": -6.547,
        "speechiness": 0.0274,
        "tempo": 81.993,
        "time_signature": 4,
        "valence": 0.199
    },
    "22": {
        "name": "紅蓮華 - From THE FIRST TAKE",
        "album": "紅蓮華 - From THE FIRST TAKE",
        "artist": "LiSA",
        "release_date": "2020-12-25",
        "length": 254960,
        "popularity": 47,
        "key": 4,
        "mode": 0,
        "danceability": 0.512,
        "acousticness": 0.729,
        "energy": 0.45,
        "instrumentalness": 0,
        "liveness": 0.213,
        "loudness": -6.776,
        "speechiness": 0.0344,
        "tempo": 123.838,
        "time_signature": 4,
        "valence": 0.334
    },
    "23": {
        "name": "炎",
        "album": "炎",
        "artist": "LiSA",
        "release_date": "2020-10-12",
        "length": 275000,
        "popularity": 70,
        "key": 2,
        "mode": 1,
        "danceability": 0.477,
        "acousticness": 0.105,
        "energy": 0.685,
        "instrumentalness": 0,
        "liveness": 0.277,
        "loudness": -4.554,
        "speechiness": 0.0325,
        "tempo": 152.04,
        "time_signature": 4,
        "valence": 0.308
    },
    "24": {
        "name": "猫 〜THE FIRST TAKE ver.〜",
        "album": "猫 〜THE FIRST TAKE ver.〜",
        "artist": "DISH//",
        "release_date": "2020-04-29",
        "length": 273233,
        "popularity": 55,
        "key": 8,
        "mode": 1,
        "danceability": 0.641,
        "acousticness": 0.564,
        "energy": 0.576,
        "instrumentalness": 0,
        "liveness": 0.114,
        "loudness": -6.772,
        "speechiness": 0.139,
        "tempo": 77.005,
        "time_signature": 4,
        "valence": 0.622
    },
    "25": {
        "name": "僕らが強く。",
        "album": "僕らが強く。",
        "artist": "DISH//",
        "release_date": "2020-08-12",
        "length": 283017,
        "popularity": 32,
        "key": 2,
        "mode": 1,
        "danceability": 0.527,
        "acousticness": 0.000964,
        "energy": 0.819,
        "instrumentalness": 0,
        "liveness": 0.214,
        "loudness": -4.64,
        "speechiness": 0.0324,
        "tempo": 112.017,
        "time_signature": 3,
        "valence": 0.412
    },
    "26": {
        "name": "BAKU",
        "album": "BAKU",
        "artist": "Ikimonogakari",
        "release_date": "2021-01-18",
        "length": 227213,
        "popularity": 52,
        "key": 1,
        "mode": 0,
        "danceability": 0.64,
        "acousticness": 0.068,
        "energy": 0.939,
        "instrumentalness": 0,
        "liveness": 0.0762,
        "loudness": -3.368,
        "speechiness": 0.0421,
        "tempo": 113.985,
        "time_signature": 4,
        "valence": 0.756
    },
    "27": {
        "name": "Walking with you",
        "album": "SKYWALK",
        "artist": "Novelbright",
        "release_date": "2018-10-03",
        "length": 223186,
        "popularity": 66,
        "key": 7,
        "mode": 1,
        "danceability": 0.422,
        "acousticness": 0.00585,
        "energy": 0.969,
        "instrumentalness": 0,
        "liveness": 0.533,
        "loudness": -0.824,
        "speechiness": 0.0591,
        "tempo": 92.524,
        "time_signature": 4,
        "valence": 0.496
    },
    "28": {
        "name": "ツキミソウ",
        "album": "ツキミソウ",
        "artist": "Novelbright",
        "release_date": "2020-12-11",
        "length": 307609,
        "popularity": 61,
        "key": 6,
        "mode": 1,
        "danceability": 0.481,
        "acousticness": 0.413,
        "energy": 0.611,
        "instrumentalness": 0,
        "liveness": 0.255,
        "loudness": -4.248,
        "speechiness": 0.0354,
        "tempo": 155.788,
        "time_signature": 4,
        "valence": 0.436
    },
    "29": {
        "name": "Beautiful",
        "album": "WHITE",
        "artist": "Superfly",
        "release_date": "2015-05-27",
        "length": 297931,
        "popularity": 54,
        "key": 3,
        "mode": 1,
        "danceability": 0.51,
        "acousticness": 0.0435,
        "energy": 0.895,
        "instrumentalness": 1.34e-06,
        "liveness": 0.123,
        "loudness": -3.321,
        "speechiness": 0.0444,
        "tempo": 144.847,
        "time_signature": 4,
        "valence": 0.356
    },
    "30": {
        "name": "ファンファーレ",
        "album": "ファンファーレ / 春夏秋冬",
        "artist": "sumika",
        "release_date": "2018-08-29",
        "length": 187480,
        "popularity": 0,
        "key": 3,
        "mode": 1,
        "danceability": 0.629,
        "acousticness": 0.0282,
        "energy": 0.945,
        "instrumentalness": 0,
        "liveness": 0.252,
        "loudness": -2.354,
        "speechiness": 0.0487,
        "tempo": 109.092,
        "time_signature": 4,
        "valence": 0.715
    },
    "31": {
        "name": "願い",
        "album": "願い",
        "artist": "sumika",
        "release_date": "2019-11-16",
        "length": 314186,
        "popularity": 43,
        "key": 2,
        "mode": 1,
        "danceability": 0.553,
        "acousticness": 0.0588,
        "energy": 0.837,
        "instrumentalness": 0,
        "liveness": 0.103,
        "loudness": -5.343,
        "speechiness": 0.0296,
        "tempo": 91.004,
        "time_signature": 4,
        "valence": 0.74
    },
    "32": {
        "name": "ファーストラヴ",
        "album": "ファーストラヴ",
        "artist": "Uru",
        "release_date": "2021-02-08",
        "length": 302253,
        "popularity": 51,
        "key": 9,
        "mode": 1,
        "danceability": 0.526,
        "acousticness": 0.853,
        "energy": 0.437,
        "instrumentalness": 0,
        "liveness": 0.12,
        "loudness": -5.38,
        "speechiness": 0.0349,
        "tempo": 74.908,
        "time_signature": 4,
        "valence": 0.165
    },
    "33": {
        "name": "Kaikai Kitan",
        "album": "Kaikai Kitan / Ao No Waltz",
        "artist": "Eve",
        "release_date": "2020-12-23",
        "length": 221426,
        "popularity": 78,
        "key": 5,
        "mode": 0,
        "danceability": 0.584,
        "acousticness": 0.0119,
        "energy": 0.911,
        "instrumentalness": 0,
        "liveness": 0.119,
        "loudness": -3.515,
        "speechiness": 0.09,
        "tempo": 92.502,
        "time_signature": 4,
        "valence": 0.606
    },
    "34": {
        "name": "Poppin' Shakin'",
        "album": "Poppin' Shakin'",
        "artist": "NiziU",
        "release_date": "2021-02-20",
        "length": 192754,
        "popularity": 56,
        "key": 4,
        "mode": 1,
        "danceability": 0.781,
        "acousticness": 0.0921,
        "energy": 0.865,
        "instrumentalness": 0.0169,
        "liveness": 0.0879,
        "loudness": -5.218,
        "speechiness": 0.0798,
        "tempo": 123.986,
        "time_signature": 4,
        "valence": 0.746
    },
    "35": {
        "name": "蕾",
        "album": "蕾",
        "artist": "GReeeeN",
        "release_date": "2021-03-04",
        "length": 207360,
        "popularity": 47,
        "key": 8,
        "mode": 1,
        "danceability": 0.634,
        "acousticness": 0.393,
        "energy": 0.646,
        "instrumentalness": 0,
        "liveness": 0.22,
        "loudness": -3.912,
        "speechiness": 0.0268,
        "tempo": 78.005,
        "time_signature": 4,
        "valence": 0.616
    },
    "36": {
        "name": "足跡",
        "album": "足跡",
        "artist": "Little Glee Monster",
        "release_date": "2020-09-02",
        "length": 255400,
        "popularity": 38,
        "key": 0,
        "mode": 1,
        "danceability": 0.42,
        "acousticness": 0.734,
        "energy": 0.578,
        "instrumentalness": 0,
        "liveness": 0.107,
        "loudness": -7.065,
        "speechiness": 0.0411,
        "tempo": 165.707,
        "time_signature": 4,
        "valence": 0.427
    },
    "37": {
        "name": "家族になろうよ",
        "album": "家族になろうよ/fighting pose",
        "artist": "Masaharu Fukuyama",
        "release_date": "2011-08-31",
        "length": 307813,
        "popularity": 55,
        "key": 8,
        "mode": 1,
        "danceability": 0.495,
        "acousticness": 0.539,
        "energy": 0.422,
        "instrumentalness": 5.46e-06,
        "liveness": 0.111,
        "loudness": -6.757,
        "speechiness": 0.0314,
        "tempo": 147.556,
        "time_signature": 4,
        "valence": 0.219
    },
    "38": {
        "name": "僕は僕を好きになる",
        "album": "僕は僕を好きになる (Special Edition)",
        "artist": "Nogizaka46",
        "release_date": "2021-01-20",
        "length": 291866,
        "popularity": 50,
        "key": 10,
        "mode": 1,
        "danceability": 0.49,
        "acousticness": 0.363,
        "energy": 0.923,
        "instrumentalness": 0,
        "liveness": 0.148,
        "loudness": -2.35,
        "speechiness": 0.0521,
        "tempo": 131.948,
        "time_signature": 4,
        "valence": 0.504
    },
    "39": {
        "name": "あとひとつ",
        "album": "ファンキーモンキーベイビーズ 4",
        "artist": "FUNKY MONKEY BABYS",
        "release_date": "2011-12-21",
        "length": 338333,
        "popularity": 56,
        "key": 7,
        "mode": 1,
        "danceability": 0.573,
        "acousticness": 0.206,
        "energy": 0.682,
        "instrumentalness": 0,
        "liveness": 0.339,
        "loudness": -4.528,
        "speechiness": 0.0255,
        "tempo": 78.993,
        "time_signature": 4,
        "valence": 0.532
    },
    "40": {
        "name": "再会 (produced by Ayase)",
        "album": "再会 (produced by Ayase)",
        "artist": "LiSA",
        "release_date": "2020-11-16",
        "length": 242166,
        "popularity": 63,
        "key": 7,
        "mode": 0,
        "danceability": 0.713,
        "acousticness": 0.315,
        "energy": 0.606,
        "instrumentalness": 0,
        "liveness": 0.262,
        "loudness": -5.718,
        "speechiness": 0.0328,
        "tempo": 90.005,
        "time_signature": 4,
        "valence": 0.492
    },
    "41": {
        "name": "感電",
        "album": "STRAY SHEEP",
        "artist": "Kenshi Yonezu",
        "release_date": "2020-08-05",
        "length": 264533,
        "popularity": 2,
        "key": 8,
        "mode": 0,
        "danceability": 0.633,
        "acousticness": 0.107,
        "energy": 0.723,
        "instrumentalness": 0,
        "liveness": 0.0818,
        "loudness": -5.733,
        "speechiness": 0.143,
        "tempo": 103.101,
        "time_signature": 4,
        "valence": 0.688
    },
    "42": {
        "name": "夜に駆ける",
        "album": "夜に駆ける",
        "artist": "YOASOBI",
        "release_date": "2019-12-15",
        "length": 261013,
        "popularity": 75,
        "key": 8,
        "mode": 1,
        "danceability": 0.67,
        "acousticness": 0.00231,
        "energy": 0.874,
        "instrumentalness": 1.72e-05,
        "liveness": 0.3,
        "loudness": -5.221,
        "speechiness": 0.0305,
        "tempo": 130.041,
        "time_signature": 4,
        "valence": 0.789
    },
    "43": {
        "name": "怪物",
        "album": "怪物",
        "artist": "YOASOBI",
        "release_date": "2021-01-06",
        "length": 206000,
        "popularity": 74,
        "key": 1,
        "mode": 1,
        "danceability": 0.627,
        "acousticness": 0.0699,
        "energy": 0.824,
        "instrumentalness": 6.57e-05,
        "liveness": 0.31,
        "loudness": -3.419,
        "speechiness": 0.118,
        "tempo": 169.935,
        "time_signature": 4,
        "valence": 0.774
    },
    "44": {
        "name": "Universe",
        "album": "Universe",
        "artist": "Official HIGE DANdism",
        "release_date": "2021-01-09",
        "length": 286099,
        "popularity": 57,
        "key": 1,
        "mode": 1,
        "danceability": 0.493,
        "acousticness": 0.227,
        "energy": 0.907,
        "instrumentalness": 1.7e-05,
        "liveness": 0.136,
        "loudness": -4.911,
        "speechiness": 0.19,
        "tempo": 185.959,
        "time_signature": 4,
        "valence": 0.596
    },
    "45": {
        "name": "Pretender",
        "album": "Traveler",
        "artist": "Official HIGE DANdism",
        "release_date": "2019-09-11",
        "length": 326842,
        "popularity": 70,
        "key": 8,
        "mode": 1,
        "danceability": 0.538,
        "acousticness": 0.047,
        "energy": 0.869,
        "instrumentalness": 0,
        "liveness": 0.14,
        "loudness": -3.464,
        "speechiness": 0.0275,
        "tempo": 91.972,
        "time_signature": 4,
        "valence": 0.369
    },
    "46": {
        "name": "桜が降る夜は",
        "album": "桜が降る夜は",
        "artist": "Aimyon",
        "release_date": "2021-02-17",
        "length": 274800,
        "popularity": 64,
        "key": 5,
        "mode": 1,
        "danceability": 0.641,
        "acousticness": 0.384,
        "energy": 0.957,
        "instrumentalness": 1.05e-06,
        "liveness": 0.218,
        "loudness": -2.574,
        "speechiness": 0.0455,
        "tempo": 106.995,
        "time_signature": 4,
        "valence": 0.71
    },
    "47": {
        "name": "虹",
        "album": "うたい去りし花",
        "artist": "Aqua Timez",
        "release_date": "2009-03-11",
        "length": 339440,
        "popularity": 54,
        "key": 10,
        "mode": 1,
        "danceability": 0.595,
        "acousticness": 0.000861,
        "energy": 0.978,
        "instrumentalness": 0,
        "liveness": 0.317,
        "loudness": -3.82,
        "speechiness": 0.0467,
        "tempo": 127.99,
        "time_signature": 4,
        "valence": 0.877
    },
    "48": {
        "name": "アイノカタチ (So Special Ver.)",
        "album": "アイノカタチ (So Special Ver.)",
        "artist": "MISIA",
        "release_date": "2020-11-11",
        "length": 265506,
        "popularity": 28,
        "key": 6,
        "mode": 1,
        "danceability": 0.504,
        "acousticness": 0.0172,
        "energy": 0.67,
        "instrumentalness": 0,
        "liveness": 0.165,
        "loudness": -6.116,
        "speechiness": 0.0277,
        "tempo": 89.989,
        "time_signature": 4,
        "valence": 0.32
    },
    "49": {
        "name": "Brand new planet",
        "album": "SOUNDTRACKS",
        "artist": "Mr.Children",
        "release_date": "2020-12-02",
        "length": 263106,
        "popularity": 50,
        "key": 2,
        "mode": 1,
        "danceability": 0.541,
        "acousticness": 0.417,
        "energy": 0.513,
        "instrumentalness": 2.83e-06,
        "liveness": 0.111,
        "loudness": -9.33,
        "speechiness": 0.0324,
        "tempo": 121.001,
        "time_signature": 4,
        "valence": 0.481
    },
    "50": {
        "name": "Documentary film",
        "album": "SOUNDTRACKS",
        "artist": "Mr.Children",
        "release_date": "2020-12-02",
        "length": 280770,
        "popularity": 45,
        "key": 5,
        "mode": 1,
        "danceability": 0.369,
        "acousticness": 0.124,
        "energy": 0.535,
        "instrumentalness": 4.88e-06,
        "liveness": 0.127,
        "loudness": -9.733,
        "speechiness": 0.0269,
        "tempo": 169.832,
        "time_signature": 4,
        "valence": 0.324
    }
}